multiplex/__init__.py
multiplex/drawable.py
multiplex/labelled.py
multiplex/legend.py
multiplex/text_util.py
multiplex/util.py
multiplex/visualization.py
multiplex/text/__init__.py
multiplex/text/annotation.py
multiplex/text/text.py
multiplex/timeseries/__init__.py
multiplex/timeseries/timeseries.py
multiplex_plot-0.2.7.dist-info/LICENSE
multiplex_plot-0.2.7.dist-info/METADATA
multiplex_plot-0.2.7.dist-info/WHEEL
multiplex_plot-0.2.7.dist-info/top_level.txt
multiplex_plot-0.2.7.dist-info/RECORD
