Metadata-Version: 2.1
Name: multiplex-plot
Version: 0.2.7
Summary: Multiplex: visualizations that tell stories
Home-page: https://github.com/NicholasMamo/multiplex-plot
Author: Nicholas Mamo
Author-email: nicholasmamo@gmail.com
License: UNKNOWN
Platform: UNKNOWN
Classifier: Development Status :: 3 - Alpha
Classifier: Programming Language :: Python :: 3
Classifier: License :: OSI Approved :: GNU General Public License v3 (GPLv3)
Classifier: Operating System :: OS Independent
Classifier: Topic :: Scientific/Engineering :: Visualization
Classifier: Intended Audience :: Developers
Classifier: Intended Audience :: Science/Research
Requires-Python: >=3
